{
  "siblings": [
    {
      "name": "Jay-r",
      "birthdate": "2006-02-14",
      "age": 19,
      "age_details": {
        "years": 19,
        "months": 6,
        "days": 27,
        "hours": 1,
        "total_years": 19.573972602739726
      }
    },
    {
      "name": "Noynoy",
      "birthdate": "2008-08-21",
      "age": 17,
      "age_details": {
        "years": 17,
        "months": 0,
        "days": 18,
        "hours": 1,
        "total_years": 17.04931506849315
      }
    },
    {
      "name": "Axel",
      "birthdate": "2024-08-20",
      "age": 1,
      "age_details": {
        "years": 1,
        "months": 0,
        "days": 15,
        "hours": 1,
        "total_years": 1.0410958904109588
      }
    }
  ],
  "last_updated": "2025-09-04",
  "last_updated_full": "September 04, 2025 09:22:56 (WITA)"
}