{
  "siblings": [
    {
      "name": "Jay-r",
      "birthdate": "2006-02-14",
      "age": 20,
      "age_details": {
        "years": 20,
        "months": 0,
        "days": 7,
        "hours": 2,
        "total_years": 20.019178082191782
      }
    },
    {
      "name": "Noynoy",
      "birthdate": "2008-08-21",
      "age": 17,
      "age_details": {
        "years": 17,
        "months": 6,
        "days": 3,
        "hours": 2,
        "total_years": 17.508219178082193
      }
    },
    {
      "name": "Axel",
      "birthdate": "2024-08-20",
      "age": 1,
      "age_details": {
        "years": 1,
        "months": 6,
        "days": 0,
        "hours": 2,
        "total_years": 1.5
      }
    }
  ],
  "last_updated": "2026-02-16",
  "last_updated_full": "February 16, 2026 10:21:45 (WITA)"
}